FSM_Core.v
// File: FSM_Core.v
// Implementasi FSM 4-Status menggunakan logika transisi JK.

module FSM_Core (
    input  logic CLK, RESET_N,
    input  logic SE, SW, OTAR, RH_IN, 

    output logic BUZZER, LED, HMD, FAN, HTR, MOT
);

    // --- Definisi Status Biner ---
    parameter S0_NOT_OCCUPIED = 2'b00;
    parameter S1_WARNING      = 2'b01;
    parameter S2_RESTING      = 2'b10;
    parameter S3_EMERGENCY    = 2'b11;

    // --- Sinyal Status Internal ---
    reg [1:0] current_state, next_state;
    
    // Sinyal Biner Q1 dan Q0 (Output dari FF Status)
    wire Q1 = current_state[1];
    wire Q0 = current_state[0];
    
    // Sinyal Input JK (Untuk Next State Logic)
    wire J1, K1, J0, K0;

    // Sinyal Kalkulasi Next State (DIKOREKSI: Dideklarasikan sebagai wire di luar always)
    wire Q1_next_calc; 
    wire Q0_next_calc; 

    // ===================================================
    // BLOK 1: Register Status (Penyimpanan Status)
    // ===================================================
    always @(posedge CLK or negedge RESET_N) begin
        if (!RESET_N) begin
            current_state <= S0_NOT_OCCUPIED;
        end else begin
            current_state <= next_state;
        end
    end

    // ===================================================
    // BLOK 2: Logika Transisi JK (Kombinasional - Menggunakan ASSIGN)
    // ===================================================
    
    // Menghitung J dan K (Logika dari Penyederhanaan QM)
    assign J1 = SE | (~SE & ~SW & OTAR);
    assign K1 = (~SE & SW) | (~SE & ~OTAR);
    assign J0 = SE | (~SE & SW);
    assign K0 = ~SE & ~SW;
    
    // Menghitung Q(n+1) secara Biner (Next State Logic)
    // Q(n+1) = J * !Q(n) + !K * Q(n)
    // Ini adalah logika kombinatorial, DIBERI NILAI menggunakan ASSIGN
    assign Q1_next_calc = (J1 & ~Q1) | (~K1 & Q1);
    assign Q0_next_calc = (J0 & ~Q0) | (~K0 & Q0);
    
    // Konversi hasil biner ke tipe State_Type (Enum) - Blok Kombinasional
    always @(*) begin
        // next_state adalah reg, diberi nilai di sini
        case ({Q1_next_calc, Q0_next_calc})
            S0_NOT_OCCUPIED: next_state = S0_NOT_OCCUPIED;
            S1_WARNING:      next_state = S1_WARNING;
            S2_RESTING:      next_state = S2_RESTING;
            S3_EMERGENCY:    next_state = S3_EMERGENCY;
            default: next_state = S0_NOT_OCCUPIED;
        endcase
    end
    
    // ===================================================
    // BLOK 3: Logika Output (Kombinasional Berdasarkan Status)
    // ===================================================
    always @(*) begin
        // Reset default output 
        BUZZER = 1'b0; LED = 1'b0; HMD = 1'b0; FAN = 1'b0; HTR = 1'b0; MOT = 1'b0;

        case (current_state)
            S0_NOT_OCCUPIED: begin
                MOT = 1'b0; // Motor: Sitting
                HMD = ~RH_IN;
                FAN = RH_IN;
                HTR = RH_IN;
            end
            S1_WARNING: begin
                LED = 1'b1; // LED ON
            end
            S2_RESTING: begin
                MOT = 1'b1; // Motor: Lying
                HMD = ~RH_IN;
                FAN = RH_IN;
                HTR = RH_IN;
            end
            S3_EMERGENCY: begin
                BUZZER = 1'b1; // Buzzer & LED ON
                LED    = 1'b1;
            end
            default: begin end
        endcase
    end

endmodule

Logic_Input.v
// File: Logic_Input.v

module Logic_Input (
    // Deklarasi Port
    input  HR_bin, BP_bin, BT_bin, LC_bin, A_bin, RH_IN,

    // OUTPUT dideklarasikan sebagai 'output wire'
    output wire SE_out, SW_out, OTAR_out, RH_FSM 
);

    // Risk_Count adalah sinyal kombinatorial
    wire [1:0] Risk_Count_wire; 
    
    // Logika Penjumlahan Risiko (Kombinasional)
    assign Risk_Count_wire = HR_bin + BP_bin + BT_bin;
    
    // Logika Sinyal Prioritas FSM (Menggunakan assign)
    
    // SE (Emergency): Risk_Count >= 2
    assign SE_out = (Risk_Count_wire >= 2); // Baris 18 diperbaiki
    
    // SW (Warning): Risk_Count = 1 DAN tidak Emergency
    assign SW_out = (Risk_Count_wire == 1) & (!SE_out); // Baris 21 diperbaiki

    // OTAR (Occupancy Target): LC AND A
    assign OTAR_out = LC_bin & A_bin; // Baris 24 diperbaiki
    
    // RH diteruskan
    assign RH_FSM = RH_IN; // Baris 27 diperbaiki

endmodule

FSM_Core_tb.v
// File: FSM_Core_tb.v
// Testbench untuk FSM_Core

`timescale 1ns / 1ps

module FSM_Core_tb;

    // Signal Declarations
    reg CLK, RESET_N, RH_tb;
    reg HR_tb, BP_tb, BT_tb; // Input Medis
    reg LC_tb, A_tb;         // Input Occupancy

    wire SE_sig, SW_sig, OTAR_sig, RH_FSM_sig;
    wire BUZZER_out, LED_out, HMD_out, FAN_out, HTR_out, MOT_out;

    // Clock Period Definition
    parameter CLK_PERIOD = 10; // 10 ns period

    // ----------------------------------------------------
    // Instansiasi Modul Logic_Input
    // ----------------------------------------------------
    Logic_Input I_LOGIC (
        .HR_bin(HR_tb), .BP_bin(BP_tb), .BT_bin(BT_tb),
        .LC_bin(LC_tb), .A_bin(A_tb), .RH_IN(RH_tb),
        .SE_out(SE_sig), .SW_out(SW_sig), .OTAR_out(OTAR_sig), 
        .RH_FSM(RH_FSM_sig)
    );

    // ----------------------------------------------------
    // Instansiasi Modul FSM_Core (Unit Under Test)
    // ----------------------------------------------------
    FSM_Core UUT_FSM (
        .CLK(CLK), .RESET_N(RESET_N),
        .SE(SE_sig), .SW(SW_sig), .OTAR(OTAR_sig), .RH_IN(RH_FSM_sig),
        .BUZZER(BUZZER_out), .LED(LED_out), .HMD(HMD_out),
        .FAN(FAN_out), .HTR(HTR_out), .MOT(MOT_out)
    );

    // Clock Generation
    initial begin
        CLK = 0;
        forever #(CLK_PERIOD / 2) CLK = ~CLK;
    end

    // Dump VCD File for GTKWave
    initial begin
        $dumpfile("fsm_dump.vcd");
        $dumpvars(0, FSM_Core_tb);
    end

    // Stimulus Generation
    initial begin
        // 1. Reset Awal
        RESET_N = 0;
        HR_tb = 0; BP_tb = 0; BT_tb = 0; LC_tb = 0; A_tb = 0; RH_tb = 0;
        # (CLK_PERIOD * 2) RESET_N = 1;
        # (CLK_PERIOD * 2) ; 

        // 2. Skenario A: S0 -> S2 (Resting/Lying)
        // Input: Medis Aman, Target Lying (OTAR=1), RH=1
        // Expected: S2, MOT=1, FAN/HTR=1
        LC_tb = 1; A_tb = 1; RH_tb = 1; 
        # (CLK_PERIOD * 4) ; 

        // 3. Skenario B: S2 -> S0 (Not Occupied/Sitting)
        // Input: Medis Aman, Target Sitting (OTAR=0), RH=0
        // Expected: S0, MOT=0, HMD=1
        LC_tb = 0; A_tb = 0; RH_tb = 0;
        # (CLK_PERIOD * 4) ;

        // 4. Skenario C: S0 -> S1 (Warning)
        // Input: HR=1 (SW=1), Medis Risiko 1, RH=1
        // Expected: S1, LED=1, Lingkungan OFF
        HR_tb = 1; BP_tb = 0; BT_tb = 0;
        LC_tb = 0; A_tb = 0; RH_tb = 1; 
        # (CLK_PERIOD * 4) ;

        // 5. Skenario D: S1 -> S3 (Emergency Override)
        // Input: HR=1, BP=1 (SE=1)
        // Expected: S3, BUZZER=1, LED=1
        BP_tb = 1;
        # (CLK_PERIOD * 4) ;
        
        // 6. Skenario E: Kembali Normal (S3 -> S0)
        // Input: Medis Aman (SE=0, SW=0)
        // Expected: S0, Semua OFF
        HR_tb = 0; BP_tb = 0;
        # (CLK_PERIOD * 4) ;

        $finish; 
    end
endmodule

fsm_dump.vcd
$date
	Mon Dec 01 10:05:10 2025
$end
$version
	Icarus Verilog
$end
$timescale
	1ps
$end
$scope module FSM_Core_tb $end
$var wire 1 ! SW_sig $end
$var wire 1 " SE_sig $end
$var wire 1 # RH_FSM_sig $end
$var wire 1 $ OTAR_sig $end
$var wire 1 % MOT_out $end
$var wire 1 & LED_out $end
$var wire 1 ' HTR_out $end
$var wire 1 ( HMD_out $end
$var wire 1 ) FAN_out $end
$var wire 1 * BUZZER_out $end
$var reg 1 + A_tb $end
$var reg 1 , BP_tb $end
$var reg 1 - BT_tb $end
$var reg 1 . CLK $end
$var reg 1 / HR_tb $end
$var reg 1 0 LC_tb $end
$var reg 1 1 RESET_N $end
$var reg 1 2 RH_tb $end
$scope module I_LOGIC $end
$var wire 1 + A_bin $end
$var wire 1 , BP_bin $end
$var wire 1 - BT_bin $end
$var wire 1 / HR_bin $end
$var wire 1 0 LC_bin $end
$var wire 1 $ OTAR_out $end
$var wire 1 # RH_FSM $end
$var wire 1 2 RH_IN $end
$var wire 1 ! SW_out $end
$var wire 1 " SE_out $end
$var wire 2 3 Risk_Count_wire [1:0] $end
$upscope $end
$scope module UUT_FSM $end
$var wire 1 . CLK $end
$var wire 1 4 J0 $end
$var wire 1 5 J1 $end
$var wire 1 6 K0 $end
$var wire 1 7 K1 $end
$var wire 1 $ OTAR $end
$var wire 1 8 Q0_next_calc $end
$var wire 1 9 Q1_next_calc $end
$var wire 1 1 RESET_N $end
$var wire 1 # RH_IN $end
$var wire 1 " SE $end
$var wire 1 ! SW $end
$var wire 1 : Q1 $end
$var wire 1 ; Q0 $end
$var reg 1 * BUZZER $end
$var reg 1 ) FAN $end
$var reg 1 ( HMD $end
$var reg 1 ' HTR $end
$var reg 1 & LED $end
$var reg 1 % MOT $end
$var reg 2 < current_state [1:0] $end
$var reg 2 = next_state [1:0] $end
$upscope $end
$upscope $end
$enddefinitions $end
#0
$dumpvars
b0 =
b0 <
0;
0:
09
08
17
16
05
04
b0 3
02
01
00
0/
0.
0-
0,
0+
0*
0)
1(
0'
0&
0%
0$
0#
0"
0!
$end
#5000
1.
#10000
0.
#15000
1.
#20000
0.
11
#25000
1.
#30000
0.
#35000
1.
#40000
b10 =
19
07
15
1'
1)
0(
1$
0.
1#
12
1+
10
#45000
1%
1'
1)
1:
b10 <
1.
#50000
0.
#55000
1.
#60000
0.
#65000
1.
#70000
0.
#75000
1.
#80000
b0 =
09
17
05
1(
1%
0'
0)
0$
0.
0#
02
0+
00
#85000
0%
1(
0:
b0 <
1.
#90000
0.
#95000
1.
#100000
0.
#105000
1.
#110000
0.
#115000
1.
#120000
b1 =
18
14
06
1'
1)
0(
1!
0.
1#
12
b1 3
1/
#125000
1&
0'
0)
1;
b1 <
1.
#130000
0.
#135000
1.
#140000
0.
#145000
1.
#150000
0.
#155000
1.
#160000
b11 =
19
07
15
0!
0.
1"
b10 3
1,
#165000
1*
1&
1:
b11 <
1.
#170000
0.
#175000
1.
#180000
0.
#185000
1.
#190000
0.
#195000
1.
#200000
09
b0 =
08
17
16
05
04
0.
0,
0"
b0 3
0/
#205000
1'
1)
0&
0*
0:
0;
b0 <
1.
